{
  "config": {
    "crediti_iniziali": 330,
    "mostra_mercato": true
  },
  "campionato": [
    {
      "nome_squadra": "Hellas Verano",
      "proprietario": "Marco",
      "partecipanti": [
        {
          "nome": "Sophia Loren",
          "prezzo": 100,
          "status": "vivo",
          "punti": 0,
          "rimborso": 0
        },
        {
          "nome": "Calvin Klein (stilista)",
          "prezzo": 20,
          "status": "vivo",
          "punti": 0,
          "rimborso": 0
        },
        {
          "nome": "Wanna Marchi",
          "prezzo": 50,
          "status": "vivo",
          "punti": 0,
          "rimborso": 0
        },
        {
          "nome": "Jim Belushi",
          "prezzo": 10,
          "status": "vivo",
          "punti": 0,
          "rimborso": 0
        },
        {
          "nome": "Silvan",
          "prezzo": 35,
          "status": "vivo",
          "punti": 0,
          "rimborso": 0
        },
        {
          "nome": "Marco Tardelli",
          "prezzo": 10,
          "status": "vivo",
          "punti": 0,
          "rimborso": 0
        },
        {
          "nome": "Kevin Spacey",
          "prezzo": 15,
          "status": "vivo",
          "punti": 0,
          "rimborso": 0
        },
        {
          "nome": "Massimo Zanetti",
          "prezzo": 10,
          "status": "vivo",
          "punti": 0,
          "rimborso": 0
        },
        {
          "nome": "Paolo Gentiloni",
          "prezzo": 10,
          "status": "vivo",
          "punti": 0,
          "rimborso": 0
        },
        {
          "nome": "Federico Faggin",
          "prezzo": 15,
          "status": "vivo",
          "punti": 0,
          "rimborso": 0
        },
        {
          "nome": "Michael McKean",
          "prezzo": 15,
          "status": "vivo",
          "punti": 0,
          "rimborso": 0
        },
        {
          "nome": "Paola Binetti",
          "prezzo": 15,
          "status": "vivo",
          "punti": 0,
          "rimborso": 0
        },
        {
          "nome": "Cristina Jorio",
          "prezzo": 20,
          "status": "vivo",
          "punti": 0,
          "rimborso": 0
        }
      ],
      "totPunti": 0,
      "capitano": "Sophia Loren"
    },
    {
      "nome_squadra": "(re)al creatore",
      "proprietario": "Emma",
      "capitano": "Mina (cantante)",
      "partecipanti": [
        {
          "nome": "Isabel Allende",
          "prezzo": 15,
          "status": "vivo",
          "punti": 0,
          "rimborso": 0
        },
        {
          "nome": "Margaret Atwood",
          "prezzo": 15,
          "status": "vivo",
          "punti": 0,
          "rimborso": 0
        },
        {
          "nome": "Tadej Pogačar",
          "prezzo": 15,
          "status": "vivo",
          "punti": 0,
          "rimborso": 0
        },
        {
          "nome": "Bella Thorne",
          "prezzo": 15,
          "status": "vivo",
          "punti": 0,
          "rimborso": 0
        },
        {
          "nome": "Mina (cantante)",
          "prezzo": 75,
          "status": "vivo",
          "punti": 0,
          "rimborso": 0
        },
        {
          "nome": "Lele Mora",
          "prezzo": 45,
          "status": "vivo",
          "punti": 0,
          "rimborso": 0
        },
        {
          "nome": "Buddy Valastro",
          "prezzo": 10,
          "status": "vivo",
          "punti": 0,
          "rimborso": 0
        },
        {
          "nome": "Adonis",
          "prezzo": 20,
          "status": "vivo",
          "punti": 0,
          "rimborso": 0
        },
        {
          "nome": "Alfredo Cospito",
          "prezzo": 20,
          "status": "vivo",
          "punti": 0,
          "rimborso": 0
        },
        {
          "nome": "Dario Argento",
          "prezzo": 45,
          "status": "vivo",
          "punti": 0,
          "rimborso": 0
        },
        {
          "nome": "John Irving",
          "prezzo": 20,
          "status": "vivo",
          "punti": 0,
          "rimborso": 0
        },
        {
          "nome": "Edoardo Bove",
          "prezzo": 25,
          "status": "vivo",
          "punti": 0,
          "rimborso": 0
        },
        {
          "nome": "Takeshi Kitano",
          "prezzo": 10,
          "status": "vivo",
          "punti": 0,
          "rimborso": 0
        }
      ],
      "totPunti": 0
    },
    {
      "nome_squadra": "Prima Morta",
      "proprietario": "Schegia",
      "partecipanti": [
        {
          "nome": "Mahmūd Abbās",
          "prezzo": 35,
          "status": "vivo",
          "punti": 0,
          "rimborso": 0
        },
        {
          "nome": "Gustav Thöni",
          "prezzo": 10,
          "status": "vivo",
          "punti": 0,
          "rimborso": 0
        },
        {
          "nome": "Nick Nolte",
          "prezzo": 15,
          "status": "vivo",
          "punti": 0,
          "rimborso": 0
        },
        {
          "nome": "Herbie Hancock",
          "prezzo": 15,
          "status": "vivo",
          "punti": 0,
          "rimborso": 0
        },
        {
          "nome": "Carlo Taormina",
          "prezzo": 20,
          "status": "vivo",
          "punti": 0,
          "rimborso": 0
        },
        {
          "nome": "Brian De Palma",
          "prezzo": 15,
          "status": "vivo",
          "punti": 0,
          "rimborso": 0
        },
        {
          "nome": "Raúl Castro",
          "prezzo": 55,
          "status": "vivo",
          "punti": 0,
          "rimborso": 0
        },
        {
          "nome": "Jon Voight",
          "prezzo": 15,
          "status": "vivo",
          "punti": 0,
          "rimborso": 0
        },
        {
          "nome": "Iva Zanicchi",
          "prezzo": 70,
          "status": "vivo",
          "punti": 0,
          "rimborso": 0
        },
        {
          "nome": "Phil Knight",
          "prezzo": 15,
          "status": "vivo",
          "punti": 0,
          "rimborso": 0
        },
        {
          "nome": "Pupi Avati",
          "prezzo": 35,
          "status": "vivo",
          "punti": 0,
          "rimborso": 0
        },
        {
          "nome": "Muhammad Yunus",
          "prezzo": 15,
          "status": "vivo",
          "punti": 0,
          "rimborso": 0
        },
        {
          "nome": "Martin Sheen",
          "prezzo": 15,
          "status": "vivo",
          "punti": 0,
          "rimborso": 0
        }
      ],
      "totPunti": 0,
      "capitano": "Iva Zanicchi"
    },
    {
      "nome_squadra": "Caronte & Tourist",
      "proprietario": "Alessandro",
      "partecipanti": [
        {
          "nome": "Giovanni Allevi",
          "prezzo": 70,
          "status": "vivo",
          "punti": 0,
          "rimborso": 0
        },
        {
          "nome": "Stephen King",
          "prezzo": 40,
          "status": "vivo",
          "punti": 0,
          "rimborso": 0
        },
        {
          "nome": "Nancy Pelosi",
          "prezzo": 25,
          "status": "vivo",
          "punti": 0,
          "rimborso": 0
        },
        {
          "nome": "Giucas Casella",
          "prezzo": 45,
          "status": "vivo",
          "punti": 0,
          "rimborso": 0
        },
        {
          "nome": "Giovanna Ralli",
          "prezzo": 20,
          "status": "vivo",
          "punti": 0,
          "rimborso": 0
        },
        {
          "nome": "Carol Burnett",
          "prezzo": 20,
          "status": "vivo",
          "punti": 0,
          "rimborso": 0
        },
        {
          "nome": "Sia (cantante)",
          "prezzo": 10,
          "status": "vivo",
          "punti": 0,
          "rimborso": 0
        },
        {
          "nome": "Carola Rackete",
          "prezzo": 10,
          "status": "vivo",
          "punti": 0,
          "rimborso": 0
        },
        {
          "nome": "Gianni Alemanno",
          "prezzo": 10,
          "status": "vivo",
          "punti": 0,
          "rimborso": 0
        },
        {
          "nome": "Giampiero Mughini",
          "prezzo": 50,
          "status": "vivo",
          "punti": 0,
          "rimborso": 0
        },
        {
          "nome": "Angela Finocchiaro",
          "prezzo": 10,
          "status": "vivo",
          "punti": 0,
          "rimborso": 0
        },
        {
          "nome": "Laura Boldrini",
          "prezzo": 10,
          "status": "vivo",
          "punti": 0,
          "rimborso": 0
        },
        {
          "nome": "Haruki Murakami",
          "prezzo": 10,
          "status": "vivo",
          "punti": 0,
          "rimborso": 0
        }
      ],
      "totPunti": 0,
      "capitano": "Giovanni Allevi"
    },
    {
      "capitano": "Emma Bonino",
      "nome_squadra": "I Concimabili",
      "partecipanti": [
        {
          "nome": "Emma Bonino",
          "prezzo": 100,
          "punti": 0,
          "rimborso": 0,
          "status": "vivo"
        },
        {
          "nome": "Paolo Condò",
          "prezzo": 10,
          "punti": 0,
          "rimborso": 0,
          "status": "vivo"
        },
        {
          "nome": "Christian De Sica",
          "prezzo": 40,
          "punti": 0,
          "rimborso": 0,
          "status": "vivo"
        },
        {
          "nome": "Corrado Augias",
          "prezzo": 60,
          "punti": 0,
          "rimborso": 0,
          "status": "vivo"
        },
        {
          "nome": "Bernie Sanders",
          "prezzo": 35,
          "punti": 0,
          "rimborso": 0,
          "status": "vivo"
        },
        {
          "nome": "Alberto Rimedio",
          "prezzo": 10,
          "punti": 0,
          "rimborso": 0,
          "status": "vivo"
        },
        {
          "nome": "Nuno Markl",
          "prezzo": 15,
          "punti": 0,
          "rimborso": 0,
          "status": "vivo"
        },
        {
          "nome": "Vince Neil",
          "prezzo": 10,
          "punti": 0,
          "rimborso": 0,
          "status": "vivo"
        },
        {
          "nome": "Caitlyn Jenner",
          "prezzo": 10,
          "punti": 0,
          "rimborso": 0,
          "status": "vivo"
        },
        {
          "nome": "Cardi B",
          "prezzo": 10,
          "punti": 0,
          "rimborso": 0,
          "status": "vivo"
        },
        {
          "nome": "Hugo Weaving",
          "prezzo": 10,
          "punti": 0,
          "rimborso": 0,
          "status": "vivo"
        },
        {
          "nome": "Jim Belushi",
          "prezzo": 10,
          "punti": 0,
          "rimborso": 0,
          "status": "vivo"
        },
        {
          "nome": "Vera Wang",
          "prezzo": 10,
          "punti": 0,
          "rimborso": 0,
          "status": "vivo"
        }
      ],
      "proprietario": "Nicola",
      "totPunti": 0
    },
    {
      "capitano": "Lino Banfi",
      "nome_squadra": "All’ultimo respiro",
      "partecipanti": [
        {
          "nome": "Lino Banfi",
          "prezzo": 100,
          "punti": 0,
          "rimborso": 0,
          "status": "vivo"
        },
        {
          "nome": "Baby Gang",
          "prezzo": 45,
          "punti": 0,
          "rimborso": 0,
          "status": "vivo"
        },
        {
          "nome": "J. D. Vance",
          "prezzo": 35,
          "punti": 0,
          "rimborso": 0,
          "status": "vivo"
        },
        {
          "nome": "Pier Luigi Bersani",
          "prezzo": 20,
          "punti": 0,
          "rimborso": 0,
          "status": "vivo"
        },
        {
          "nome": "Anna Oxa",
          "prezzo": 20,
          "punti": 0,
          "rimborso": 0,
          "status": "vivo"
        },
        {
          "nome": "Sal Da Vinci",
          "prezzo": 15,
          "punti": 0,
          "rimborso": 0,
          "status": "vivo"
        },
        {
          "nome": "Mojtaba Khamenei",
          "prezzo": 60,
          "punti": 0,
          "rimborso": 0,
          "status": "vivo"
        },
        {
          "nome": "Ibrahim Traoré (militare)",
          "prezzo": 20,
          "punti": 0,
          "rimborso": 0,
          "status": "vivo"
        },
        {
          "nome": "Alba Parietti",
          "prezzo": 15,
          "punti": 0,
          "rimborso": 0,
          "status": "vivo"
        }
      ],
      "proprietario": "Anna",
      "totPunti": 0
    },
    {
      "capitano": "James Hong",
      "nome_squadra": "Zero fama, zero bara",
      "partecipanti": [
        {
          "nome": "Abdelmadjid Tebboune",
          "prezzo": 15,
          "punti": 0,
          "rimborso": 0,
          "status": "vivo"
        },
        {
          "nome": "Liliana Segre",
          "prezzo": 100,
          "punti": 0,
          "rimborso": 0,
          "status": "vivo"
        },
        {
          "nome": "Bianca Pitzorno",
          "prezzo": 15,
          "punti": 0,
          "rimborso": 0,
          "status": "vivo"
        },
        {
          "nome": "António Guterres",
          "prezzo": 10,
          "punti": 0,
          "rimborso": 0,
          "status": "vivo"
        },
        {
          "nome": "Ban Ki-moon",
          "prezzo": 15,
          "punti": 0,
          "rimborso": 0,
          "status": "vivo"
        },
        {
          "nome": "Bernie Sanders",
          "prezzo": 35,
          "punti": 0,
          "rimborso": 0,
          "status": "vivo"
        },
        {
          "nome": "Matteo Piantedosi",
          "prezzo": 10,
          "punti": 0,
          "rimborso": 0,
          "status": "vivo"
        },
        {
          "nome": "Babaman",
          "prezzo": 10,
          "punti": 0,
          "rimborso": 0,
          "status": "vivo"
        },
        {
          "nome": "Paul Biya",
          "prezzo": 40,
          "punti": 0,
          "rimborso": 0,
          "status": "vivo"
        },
        {
          "nome": "Chuck Grassley",
          "prezzo": 20,
          "punti": 0,
          "rimborso": 0,
          "status": "vivo"
        },
        {
          "nome": "James Hong",
          "prezzo": 25,
          "punti": 0,
          "rimborso": 0,
          "status": "vivo"
        },
        {
          "nome": "Francesco Lollobrigida",
          "prezzo": 15,
          "punti": 0,
          "rimborso": 0,
          "status": "vivo"
        },
        {
          "nome": "Anna Maria Bernini",
          "prezzo": 15,
          "punti": 0,
          "rimborso": 0,
          "status": "vivo"
        }
      ],
      "proprietario": "Lisa",
      "totPunti": 0
    },
    {
      "nome_squadra": "I down di Ruffini",
      "proprietario": "Andrea",
      "partecipanti": [
        {
          "nome": "Andrea Bocelli",
          "prezzo": 35,
          "status": "vivo",
          "punti": 0,
          "rimborso": 0
        },
        {
          "nome": "Paolo Ruffini (attore)",
          "prezzo": 20,
          "status": "vivo",
          "punti": 0,
          "rimborso": 0
        },
        {
          "nome": "Iginio Massari",
          "prezzo": 50,
          "status": "vivo",
          "punti": 0,
          "rimborso": 0
        },
        {
          "nome": "Angelo Bonelli",
          "prezzo": 10,
          "status": "vivo",
          "punti": 0,
          "rimborso": 0
        },
        {
          "nome": "Laura Pausini",
          "prezzo": 15,
          "status": "vivo",
          "punti": 0,
          "rimborso": 0
        },
        {
          "nome": "Antonello Venditti",
          "prezzo": 45,
          "status": "vivo",
          "punti": 0,
          "rimborso": 0
        },
        {
          "nome": "Olly",
          "prezzo": 15,
          "status": "vivo",
          "punti": 0,
          "rimborso": 0
        },
        {
          "nome": "Roberto Benigni",
          "prezzo": 55,
          "status": "vivo",
          "punti": 0,
          "rimborso": 0
        },
        {
          "nome": "Quentin Tarantino",
          "prezzo": 20,
          "status": "vivo",
          "punti": 0,
          "rimborso": 0
        },
        {
          "nome": "Sofia di Grecia",
          "prezzo": 20,
          "status": "vivo",
          "punti": 0,
          "rimborso": 0
        },
        {
          "nome": "Eleonora Brigliadori",
          "prezzo": 10,
          "status": "vivo",
          "punti": 0,
          "rimborso": 0
        },
        {
          "nome": "Antonia Fraser",
          "prezzo": 25,
          "status": "vivo",
          "punti": 0,
          "rimborso": 0
        },
        {
          "nome": "Francesca Cipriani",
          "prezzo": 10,
          "status": "vivo",
          "punti": 0,
          "rimborso": 0
        }
      ],
      "totPunti": 0,
      "capitano": "Roberto Benigni"
    },
    {
      "nome_squadra": "Breaking Dead",
      "proprietario": "Krystal",
      "partecipanti": [
        {
          "nome": "Lazza",
          "prezzo": 10,
          "status": "vivo",
          "punti": 0,
          "rimborso": 0
        },
        {
          "nome": "Donatella Versace",
          "prezzo": 50,
          "status": "vivo",
          "punti": 0,
          "rimborso": 0
        },
        {
          "nome": "Carlo III del Regno Unito",
          "prezzo": 100,
          "status": "vivo",
          "punti": 0,
          "rimborso": 0
        },
        {
          "nome": "Alexandria Ocasio-Cortez",
          "prezzo": 10,
          "status": "vivo",
          "punti": 0,
          "rimborso": 0
        },
        {
          "nome": "Bill Gates",
          "prezzo": 30,
          "status": "vivo",
          "punti": 0,
          "rimborso": 0
        },
        {
          "nome": "Lil Nas X",
          "prezzo": 10,
          "status": "vivo",
          "punti": 0,
          "rimborso": 0
        },
        {
          "nome": "Alessandro Baricco",
          "prezzo": 25,
          "status": "vivo",
          "punti": 0,
          "rimborso": 0
        },
        {
          "nome": "Madonna (cantante)",
          "prezzo": 40,
          "status": "vivo",
          "punti": 0,
          "rimborso": 0
        },
        {
          "nome": "Paul Anderson",
          "prezzo": 15,
          "status": "vivo",
          "punti": 0,
          "rimborso": 0
        },
        {
          "nome": "Giulio Golia",
          "prezzo": 10,
          "status": "vivo",
          "punti": 0,
          "rimborso": 0
        },
        {
          "nome": "Luca Argentero",
          "prezzo": 10,
          "status": "vivo",
          "punti": 0,
          "rimborso": 0
        },
        {
          "nome": "Fabio Rovazzi",
          "prezzo": 10,
          "status": "vivo",
          "punti": 0,
          "rimborso": 0
        },
        {
          "nome": "Elena Sofia Ricci",
          "prezzo": 10,
          "status": "vivo",
          "punti": 0,
          "rimborso": 0
        }
      ],
      "totPunti": 0,
      "capitano": "Carlo III del Regno Unito"
    },
    {
      "capitano": "Benjamin Netanyahu",
      "nome_squadra": "Nadia Taffo",
      "partecipanti": [
        {
          "nome": "Benjamin Netanyahu",
          "prezzo": 100,
          "punti": 0,
          "rimborso": 0,
          "status": "vivo"
        },
        {
          "nome": "Gabriele Gravina",
          "prezzo": 25,
          "punti": 0,
          "rimborso": 0,
          "status": "vivo"
        },
        {
          "nome": "Claudio Lotito",
          "prezzo": 40,
          "punti": 0,
          "rimborso": 0,
          "status": "vivo"
        },
        {
          "nome": "Michele Bravi",
          "prezzo": 10,
          "punti": 0,
          "rimborso": 0,
          "status": "vivo"
        },
        {
          "nome": "Antonella Clerici",
          "prezzo": 20,
          "punti": 0,
          "rimborso": 0,
          "status": "vivo"
        },
        {
          "nome": "Elodie (cantante)",
          "prezzo": 15,
          "punti": 0,
          "rimborso": 0,
          "status": "vivo"
        },
        {
          "nome": "Luchè",
          "prezzo": 10,
          "punti": 0,
          "rimborso": 0,
          "status": "vivo"
        },
        {
          "nome": "Geolier",
          "prezzo": 15,
          "punti": 0,
          "rimborso": 0,
          "status": "vivo"
        },
        {
          "nome": "Joe Rogan",
          "prezzo": 10,
          "punti": 0,
          "rimborso": 0,
          "status": "vivo"
        },
        {
          "nome": "Daniel Radcliffe",
          "prezzo": 15,
          "punti": 0,
          "rimborso": 0,
          "status": "vivo"
        },
        {
          "nome": "Fiorella Mannoia",
          "prezzo": 25,
          "punti": 0,
          "rimborso": 0,
          "status": "vivo"
        },
        {
          "nome": "Gigi D'Alessio",
          "prezzo": 30,
          "punti": 0,
          "rimborso": 0,
          "status": "vivo"
        },
        {
          "nome": "Olly",
          "prezzo": 15,
          "punti": 0,
          "rimborso": 0,
          "status": "vivo"
        }
      ],
      "proprietario": "Samoggino",
      "totPunti": 0
    },
    {
      "nome_squadra": "Chi vivrà vedrà",
      "partecipanti": [],
      "proprietario": "Federica",
      "totPunti": 0
    }
  ]
}